audio_augment/__init__.py
audio_augment/augment.py
AudioAugment-0.0.3.dist-info/LICENSE.txt
AudioAugment-0.0.3.dist-info/METADATA
AudioAugment-0.0.3.dist-info/WHEEL
AudioAugment-0.0.3.dist-info/top_level.txt
AudioAugment-0.0.3.dist-info/RECORD
