Metadata-Version: 2.1
Name: AudioAugment
Version: 0.0.3
Summary: Audio data augmentation tool for machine learning projects
Home-page: https://github.com/wesleyLaurence/Audio-Augment
Author: Wesley Laurence
Author-email: wesleylaurencetech@gmail.com
License: UNKNOWN
Platform: UNKNOWN
Classifier: Programming Language :: Python :: 3
Classifier: License :: OSI Approved :: MIT License
Classifier: Operating System :: OS Independent
Requires-Python: >=3.6
Requires-Dist: numpy
Requires-Dist: pandas
Requires-Dist: matplotlib
Requires-Dist: librosa
Requires-Dist: soundfile
Requires-Dist: scipy
